djangotables/__init__.py
djangotables/tables/__init__.py
djangotables/tables/table.py
djangotables/tables/fields/__init__.py
djangotables/tables/fields/field.py
djangotables/tables/filters/__init__.py
djangotables-0.0.3.dist-info/LICENSE
djangotables-0.0.3.dist-info/METADATA
djangotables-0.0.3.dist-info/WHEEL
djangotables-0.0.3.dist-info/top_level.txt
djangotables-0.0.3.dist-info/RECORD
