Metadata-Version: 2.1
Name: djangotables
Version: 0.0.3
Summary: Djangotables is a simple library for generating html tables with Django Framework using model data like django forms.
Home-page: https://github.com/AgeuMatheus/djangotables
Author: Ageu Matheus
Author-email: ageumatheus1@gmail.com
Maintainer: Ageu Matheus
Maintainer-email: ageumatheus1@gmail.com
License: MIT License
Project-URL: Changelog, https://github.com/AgeuMatheus/djangotables/blob/master/HISTORY.md
Keywords: django,tables,djangotables
Platform: UNKNOWN
Classifier: Environment :: Web Environment
Classifier: Framework :: Django
Classifier: Framework :: Django :: 2.2
Classifier: Intended Audience :: Developers
Classifier: License :: OSI Approved :: MIT License
Classifier: Operating System :: OS Independent
Classifier: Programming Language :: Python
Classifier: Programming Language :: Python :: 3
Classifier: Programming Language :: Python :: 3.5
Classifier: Programming Language :: Python :: 3.6
Classifier: Programming Language :: Python :: 3.7
Classifier: Topic :: Software Development :: Libraries :: Application Frameworks
Classifier: Topic :: Software Development :: Libraries :: Python Modules
Requires-Python: >=3.6
Requires-Dist: Django (>=2)
